swat/lib/linux/__init__.py
swat/lib/mac/_py310swat.na
swat/lib/mac/__init__.py
swat/lib/__init__.py
swat/lib/win/__init__.py
swat/exceptions.py
swat/logging.py
swat/magics.py
swat/utils/datetime.py
swat/utils/args.py
swat/utils/compat.py
swat/utils/__init__.py
swat/utils/json.py
swat/utils/authinfo.py
swat/utils/keyword.py
swat/utils/config.py
swat/utils/decorators.py
swat/utils/testing.py
swat/utils/xdict.py
swat/utils/testingmocks.py
swat/cas/request.py
swat/cas/dbapi.py
swat/cas/transformers.py
swat/cas/magics.py
swat/cas/utils/datetime.py
swat/cas/utils/params.py
swat/cas/utils/__init__.py
swat/cas/utils/tk.py
swat/cas/utils/misc.py
swat/cas/__init__.py
swat/cas/actions.py
swat/cas/datamsghandlers.py
swat/cas/connection.py
swat/cas/table.py
swat/cas/types.py
swat/cas/response.py
swat/cas/results.py
swat/cas/rest/message.py
swat/cas/rest/error.py
swat/cas/rest/__init__.py
swat/cas/rest/connection.py
swat/cas/rest/table.py
swat/cas/rest/response.py
swat/cas/rest/value.py
swat/__init__.py
swat/formatter.py
swat/clib.py
swat/dataframe.py
swat/datamsghandlers.py
swat/render/generic.py
swat/render/__init__.py
swat/render/html.py
swat/tests/test_types.py
swat/tests/cas/test_csess.py
swat/tests/cas/test_results.py
swat/tests/cas/test_functions.py
swat/tests/cas/__init__.py
swat/tests/cas/test_datetime.py
swat/tests/cas/test_basics.py
swat/tests/cas/test_response.py
swat/tests/cas/test_bygroups.py
swat/tests/cas/test_datamsg.py
swat/tests/cas/test_echo.py
swat/tests/cas/test_table.py
swat/tests/cas/test_casa.py
swat/tests/cas/test_builtins.py
swat/tests/cas/test_params.py
swat/tests/cas/test_connection.py
swat/tests/cas/test_datapreprocess.py
swat/tests/cas/test_imstat.py
swat/tests/__init__.py
swat/tests/test_xdict.py
swat/tests/test_keyword.py
swat/tests/test_dataframe.py
swat/tests/datasources/cars_a.csv
swat/tests/datasources/datetimes.csv
swat/tests/datasources/cars.tsv
swat/tests/datasources/datetime.csv
swat/tests/datasources/cars_single.sashdat
swat-1.17.0.dist-info/METADATA
swat-1.17.0.dist-info/metadata.json
swat-1.17.0.dist-info/WHEEL
swat-1.17.0.dist-info/top_level.txt
swat-1.17.0.dist-info/RECORD
