Metadata-Version: 2.1
Name: swat
Version: 1.17.0
Summary: SAS Scripting Wrapper for Analytics Transfer (SWAT)
Home-page: http://github.com/sassoftware/python-swat/
Author: SAS
Author-email: Kevin.Smith@sas.com
License: Apache v2.0 (SWAT) + SAS Additional Functionality (SAS TK)
Requires-Dist: pandas (>= 0.16.0)
Requires-Dist: pytz
Requires-Dist: six (>= 1.9.0)
Requires-Dist: requests
Requires-Dist: urllib3
Platform: any
Classifier: Development Status :: 5 - Production/Stable
Classifier: Environment :: Console
Classifier: Intended Audience :: Science/Research
Classifier: Programming Language :: Python
Classifier: Programming Language :: Python :: 3
Classifier: Programming Language :: Python :: 3.7
Classifier: Programming Language :: Python :: 3.8
Classifier: Programming Language :: Python :: 3.9
Classifier: Programming Language :: Python :: 3.10
Classifier: Programming Language :: Python :: 3.11
Classifier: Programming Language :: Python :: 3.12
Classifier: Programming Language :: Python :: 3.13
Classifier: Topic :: Scientific/Engineering
